pokehelpyer/__init__.py
pokehelpyer/pokehelpyer.py
pokehelpyer-0.1.8.dist-info/METADATA
pokehelpyer-0.1.8.dist-info/WHEEL
pokehelpyer-0.1.8.dist-info/LICENSE
pokehelpyer-0.1.8.dist-info/RECORD
