Metadata-Version: 2.1
Name: pokehelpyer
Version: 0.1.8
Summary: Assists in building teams of various pokemon types based on weaknesses and resistances
License: MIT
Author: Sneha Sunil, Jakob Thoms, Ritisha Sharma, Raul Aguilar
Requires-Python: >=3.9
Classifier: License :: OSI Approved :: MIT License
Classifier: Programming Language :: Python :: 3
Classifier: Programming Language :: Python :: 3.9
Classifier: Programming Language :: Python :: 3.10
Classifier: Programming Language :: Python :: 3.11
Requires-Dist: numpy (>=1.24.1)
Requires-Dist: pandas (>=1.5.2)
Requires-Dist: python-semantic-release (>=7.33.0,<8.0.0)
